{
  "base_name": "football_helmet",
  "click_points": [
    [
      135,
      613
    ],
    [
      322,
      638
    ],
    [
      659,
      581
    ],
    [
      850,
      379
    ],
    [
      539,
      796
    ],
    [
      350,
      878
    ],
    [
      414,
      634
    ],
    [
      1006,
      765
    ],
    [
      527,
      367
    ],
    [
      615,
      258
    ]
  ],
  "circle_radius": 474,
  "dots": [
    {
      "image": "football_helmet_mooney_dot_on1.jpg",
      "label": "on",
      "type": "mooney",
      "dot_number": 1,
      "x": 1074,
      "y": 600
    },
    {
      "image": "football_helmet_mooney_dot_on2.jpg",
      "label": "on",
      "type": "mooney",
      "dot_number": 2,
      "x": 1059,
      "y": 717
    },
    {
      "image": "football_helmet_mooney_dot_on3.jpg",
      "label": "on",
      "type": "mooney",
      "dot_number": 3,
      "x": 1015,
      "y": 828
    },
    {
      "image": "football_helmet_mooney_dot_on4.jpg",
      "label": "on",
      "type": "mooney",
      "dot_number": 4,
      "x": 945,
      "y": 924
    },
    {
      "image": "football_helmet_mooney_dot_on5.jpg",
      "label": "on",
      "type": "mooney",
      "dot_number": 5,
      "x": 853,
      "y": 1000
    },
    {
      "image": "football_helmet_mooney_dot_on6.jpg",
      "label": "on",
      "type": "mooney",
      "dot_number": 6,
      "x": 346,
      "y": 1000
    },
    {
      "image": "football_helmet_mooney_dot_on7.jpg",
      "label": "on",
      "type": "mooney",
      "dot_number": 7,
      "x": 126,
      "y": 599
    },
    {
      "image": "football_helmet_mooney_dot_on8.jpg",
      "label": "on",
      "type": "mooney",
      "dot_number": 8,
      "x": 853,
      "y": 199
    },
    {
      "image": "football_helmet_mooney_dot_off1.jpg",
      "label": "off",
      "type": "mooney",
      "dot_number": 1,
      "x": 629,
      "y": 1073
    },
    {
      "image": "football_helmet_mooney_dot_off2.jpg",
      "label": "off",
      "type": "mooney",
      "dot_number": 2,
      "x": 570,
      "y": 1073
    },
    {
      "image": "football_helmet_mooney_dot_off3.jpg",
      "label": "off",
      "type": "mooney",
      "dot_number": 3,
      "x": 140,
      "y": 482
    },
    {
      "image": "football_helmet_mooney_dot_off4.jpg",
      "label": "off",
      "type": "mooney",
      "dot_number": 4,
      "x": 159,
      "y": 425
    },
    {
      "image": "football_helmet_mooney_dot_off5.jpg",
      "label": "off",
      "type": "mooney",
      "dot_number": 5,
      "x": 184,
      "y": 371
    },
    {
      "image": "football_helmet_mooney_dot_off6.jpg",
      "label": "off",
      "type": "mooney",
      "dot_number": 6,
      "x": 216,
      "y": 321
    },
    {
      "image": "football_helmet_mooney_dot_off7.jpg",
      "label": "off",
      "type": "mooney",
      "dot_number": 7,
      "x": 254,
      "y": 275
    },
    {
      "image": "football_helmet_mooney_dot_off8.jpg",
      "label": "off",
      "type": "mooney",
      "dot_number": 8,
      "x": 297,
      "y": 234
    }
  ]
}